langchain_plainid/__init__.py
langchain_plainid/category_classifier_provider.py
langchain_plainid/filter_provider.py
langchain_plainid/llm_category_classifier_provider.py
langchain_plainid/plainid_anonymizer.py
langchain_plainid/plainid_categorizer.py
langchain_plainid/plainid_client.py
langchain_plainid/plainid_default_query_translator.py
langchain_plainid/plainid_exceptions.py
langchain_plainid/plainid_filter_provider.py
langchain_plainid/plainid_permissions_provider.py
langchain_plainid/plainid_retriever.py
langchain_plainid/readme.md
langchain_plainid/zeroshot_category_classifier_provider.py
langchain_plainid-0.2.8.2.dist-info/METADATA
langchain_plainid-0.2.8.2.dist-info/WHEEL
langchain_plainid-0.2.8.2.dist-info/RECORD
