Metadata-Version: 2.1
Name: langchain_plainid
Version: 0.2.8.2
Summary: PlainID LangChain library
Author: PlainID
Requires-Python: >=3.9,<=3.12
Classifier: License :: OSI Approved :: MIT License
Classifier: Operating System :: OS Independent
Classifier: Programming Language :: Python :: 3
Classifier: Programming Language :: Python :: 3.9
Classifier: Programming Language :: Python :: 3.10
Classifier: Programming Language :: Python :: 3.11
Classifier: Programming Language :: Python :: 3.12
Requires-Dist: langchain-chroma (>=0.2.3)
Requires-Dist: langchain-community (>=0.3.23,<0.4.0)
Requires-Dist: langchain-core (>=0.3.58,<0.4.0)
Requires-Dist: langchain-ollama (>=0.3.2,<0.4.0)
Requires-Dist: onnxruntime (==1.19.0)
Requires-Dist: presidio-analyzer (>=2.2.358,<3.0.0)
Requires-Dist: presidio-anonymizer (>=2.2.358,<3.0.0)
Requires-Dist: pydantic (>=2.10.6,<3.0.0)
Requires-Dist: requests (>=2.32.3,<3.0.0)
Requires-Dist: transformers (>=4.51.3,<5.0.0)
Requires-Dist: types-requests (>=2.32.0.20250328,<3.0.0.0)
